autosubs/__init__.py
autosubs/api/__init__.py
autosubs/cli/__init__.py
autosubs/cli/burn.py
autosubs/cli/convert.py
autosubs/cli/framerate.py
autosubs/cli/generate.py
autosubs/cli/main.py
autosubs/cli/sync.py
autosubs/cli/transcribe.py
autosubs/cli/utils.py
autosubs/core/__init__.py
autosubs/core/builder.py
autosubs/core/burner.py
autosubs/core/encoding.py
autosubs/core/generator.py
autosubs/core/parser.py
autosubs/core/styler.py
autosubs/core/transcriber.py
autosubs/core/word_segmenter.py
autosubs/models/__init__.py
autosubs/models/enums.py
autosubs/models/formats.py
autosubs/models/transcription.py
autosubs/models/whisper.py
autosubs/models/styles/__init__.py
autosubs/models/styles/domain.py
autosubs/models/styles/schemas.py
autosubs/models/subtitles/__init__.py
autosubs/models/subtitles/ass.py
autosubs/models/subtitles/base.py
auto_subs-0.7.1.dist-info/METADATA
auto_subs-0.7.1.dist-info/WHEEL
auto_subs-0.7.1.dist-info/entry_points.txt
auto_subs-0.7.1.dist-info/licenses/LICENSE
auto_subs-0.7.1.dist-info/RECORD
