Metadata-Version: 2.4
Name: auto-subs
Version: 0.7.1
Summary: A powerful, local-first library and CLI for video transcription and subtitle generation using Whisper.
Project-URL: Homepage, https://github.com/mateusz-kow/auto-subs
Project-URL: Repository, https://github.com/mateusz-kow/auto-subs
Author-email: Mateusz Kowalski <kowalski.mateusz.1lo1@gmail.com>
License: Copyright 2025 Mateusz Kowalski
License-File: LICENSE
Classifier: Development Status :: 3 - Alpha
Classifier: Intended Audience :: Developers
Classifier: Intended Audience :: End Users/Desktop
Classifier: License :: OSI Approved :: MIT License
Classifier: Topic :: Multimedia :: Video
Classifier: Topic :: Scientific/Engineering :: Artificial Intelligence
Classifier: Topic :: Text Processing
Requires-Python: >=3.11
Requires-Dist: pydantic~=2.12.0
Requires-Dist: regex~=2025.7.34
Provides-Extra: cli
Requires-Dist: typer~=0.20.0; extra == 'cli'
Provides-Extra: dev
Requires-Dist: mypy~=1.18.2; extra == 'dev'
Requires-Dist: pre-commit~=4.3.0; extra == 'dev'
Requires-Dist: pytest-cov~=7.0.0; extra == 'dev'
Requires-Dist: pytest~=8.4.2; extra == 'dev'
Requires-Dist: ruff~=0.14.0; extra == 'dev'
Requires-Dist: types-regex; extra == 'dev'
Provides-Extra: encoding
Requires-Dist: charset-normalizer~=3.4.0; extra == 'encoding'
Provides-Extra: transcribe
Requires-Dist: openai-whisper; extra == 'transcribe'
